adspower_api/__init__.py
adspower_api/client.py
adspower_api/models.py
bitnet_api/__init__.py
bitnet_api/client.py
bitnet_api/models.py
bitnet_api-3.0.9.dist-info/licenses/LICENSE
flywing_api/__init__.py
flywing_api/client.py
flywing_api/models.py
bitnet_api-3.0.9.dist-info/METADATA
bitnet_api-3.0.9.dist-info/WHEEL
bitnet_api-3.0.9.dist-info/top_level.txt
bitnet_api-3.0.9.dist-info/RECORD
