Metadata-Version: 2.4
Name: bitnet-api
Version: 3.0.9
Summary: Python SDK for Bitnet Browser API with clean entity-based responses
Home-page: https://github.com/yourusername/bitnet-api
Author: Bitnet API SDK
Author-email: Bitnet API SDK <dekinsq@gmail.com>
License: MIT
Project-URL: Homepage, https://github.com/dekinsq/bit_api
Project-URL: Bug Tracker, https://github.com/dekinsq/bit_api/issues
Project-URL: Documentation, https://github.com/dekinsq/bit_api#readme
Classifier: Programming Language :: Python :: 3
Classifier: License :: OSI Approved :: MIT License
Classifier: Operating System :: OS Independent
Requires-Python: >=3.6
License-File: LICENSE
Requires-Dist: requests>=2.25.0
Dynamic: author
Dynamic: home-page
Dynamic: license-file
Dynamic: requires-python
